runner/__init__.py
runner/config.json
runner/highlighter.py
runner/main.py
runner/runner.py
runner/runner_adb.json
runner/runner_common.json
runner/runner_network.json
runner/runner_ui.py
runner/runner_windwos.json
qtrunner-0.0.6.dist-info/LICENSE
qtrunner-0.0.6.dist-info/METADATA
qtrunner-0.0.6.dist-info/WHEEL
qtrunner-0.0.6.dist-info/entry_points.txt
qtrunner-0.0.6.dist-info/top_level.txt
qtrunner-0.0.6.dist-info/RECORD
