Metadata-Version: 2.1
Name: qtrunner
Version: 0.0.6
Summary: 快速命令启动器
Home-page: https://github.com/notmmao/runner
Author: hufeng.mao
Author-email: hufeng.mao@carota.ai
License: MIT
Keywords: qt,launcher
Platform: windows
Requires-Python: >=3.6
License-File: LICENSE
Requires-Dist: pyqt5
Requires-Dist: qtawesome
